Hql/Context.py
Hql/Exceptions.py
Hql/Features.py
Hql/Helpers.py
Hql/PolarsTools.py
Hql/Query.py
Hql/Threading.py
Hql/__init__.py
Hql/__main__.py
Hql/Apiserver/__init__.py
Hql/Compiler/BranchDescriptor.py
Hql/Compiler/Compiler.py
Hql/Compiler/Hql.py
Hql/Compiler/InstructionSet.py
Hql/Compiler/Kusto.py
Hql/Compiler/Lucene.py
Hql/Compiler/QueryDSL.py
Hql/Compiler/__init__.py
Hql/Compiler/Splunk/SplunkOps.py
Hql/Compiler/Splunk/__init__.py
Hql/Compiler/Sql/Expressions.py
Hql/Compiler/Sql/Statements.py
Hql/Compiler/Sql/__init__.py
Hql/Config/__init__.py
Hql/Data/Schema.py
Hql/Data/Series.py
Hql/Data/Tables.py
Hql/Data/__init__.py
Hql/Expressions/Aggregation.py
Hql/Expressions/Functions.py
Hql/Expressions/Literals.py
Hql/Expressions/Logic.py
Hql/Expressions/References.py
Hql/Expressions/__init__.py
Hql/Expressions/__proto__.py
Hql/Expressions/Regex/.gitignore
Hql/Expressions/Regex/__init__.py
Hql/Expressions/Regex/grammar/PCRELexer.g4
Hql/Expressions/Regex/grammar/PCREParser.g4
Hql/Expressions/Regex/grammar/PCREParser.py
Hql/Expressions/Regex/grammar/PCREParserVisitor.py
Hql/Expressions/Regex/grammar/README.md
Hql/Expressions/Regex/grammar/regen.sh
Hql/Expressions/Regex/grammar/setup-antlr4.sh
Hql/Expressions/Regex/grammar/antlr4/.gitkeep
Hql/Functions/__init__.py
Hql/Functions/ago.py
Hql/Functions/base64.py
Hql/Functions/bincount.py
Hql/Functions/category.py
Hql/Functions/count.py
Hql/Functions/database.py
Hql/Functions/dfir_iris.py
Hql/Functions/file.py
Hql/Functions/hql_len.py
Hql/Functions/hqlnot.py
Hql/Functions/http.py
Hql/Functions/index.py
Hql/Functions/ip4subnet.py
Hql/Functions/isnotempty.py
Hql/Functions/macro.py
Hql/Functions/make_mv.py
Hql/Functions/null.py
Hql/Functions/product.py
Hql/Functions/scot4.py
Hql/Functions/series_stat.py
Hql/Functions/service.py
Hql/Functions/template.py
Hql/Functions/tolower.py
Hql/Functions/typecasting.py
Hql/Functions/wide.py
Hql/Hac/.gitignore
Hql/Hac/Doc.py
Hql/Hac/Engine.py
Hql/Hac/Parser.py
Hql/Hac/Sources.py
pyhql-0.0.9.dist-info/METADATA
pyhql-0.0.9.dist-info/WHEEL
pyhql-0.0.9.dist-info/licenses/LICENSE
pyhql-0.0.9.dist-info/RECORD
