Metadata-Version: 2.4
Name: pyhql
Version: 0.0.9
Summary: Hash query language, a universal Query Language
Project-URL: Homepage, https://github.com/Hashfastr/Hql
Project-URL: Issues, https://github.com/Hashfastr/Hql/issues
Author-email: Sylvain Jones <sylvainjones+hql@hashfastr.com>
Maintainer-email: Sylvain Jones <sylvainjones+hql@hashfastr.com>
License-Expression: MIT
License-File: LICENSE
Classifier: License :: OSI Approved :: MIT License
Classifier: Operating System :: OS Independent
Classifier: Programming Language :: Python :: 3
Requires-Python: >=3.9
Requires-Dist: aiohttp
Requires-Dist: antlr4-python3-runtime==4.13.2
Requires-Dist: boto3
Requires-Dist: dfir-iris-client
Requires-Dist: elasticsearch
Requires-Dist: fastapi
Requires-Dist: ndjson
Requires-Dist: numpy
Requires-Dist: opensearch-py
Requires-Dist: oyaml
Requires-Dist: polars
Requires-Dist: requests
Requires-Dist: splunk-sdk
Requires-Dist: uvicorn
